odoo/addons/website_legal_page/README.rst
odoo/addons/website_legal_page/__init__.py
odoo/addons/website_legal_page/__manifest__.py
odoo/addons/website_legal_page/hooks.py
odoo/addons/website_legal_page/controllers/__init__.py
odoo/addons/website_legal_page/controllers/main.py
odoo/addons/website_legal_page/i18n/bg.po
odoo/addons/website_legal_page/i18n/ca.po
odoo/addons/website_legal_page/i18n/de.po
odoo/addons/website_legal_page/i18n/el_GR.po
odoo/addons/website_legal_page/i18n/es.po
odoo/addons/website_legal_page/i18n/fr.po
odoo/addons/website_legal_page/i18n/hr_HR.po
odoo/addons/website_legal_page/i18n/it.po
odoo/addons/website_legal_page/i18n/nb_NO.po
odoo/addons/website_legal_page/i18n/nl.po
odoo/addons/website_legal_page/i18n/pt_BR.po
odoo/addons/website_legal_page/i18n/pt_PT.po
odoo/addons/website_legal_page/i18n/ru.po
odoo/addons/website_legal_page/i18n/sl.po
odoo/addons/website_legal_page/i18n/website_legal_page.pot
odoo/addons/website_legal_page/migrations/13.0.1.0.0/post-migrate.py
odoo/addons/website_legal_page/readme/CONTRIBUTORS.rst
odoo/addons/website_legal_page/readme/CREDITS.rst
odoo/addons/website_legal_page/readme/DESCRIPTION.rst
odoo/addons/website_legal_page/readme/USAGE.rst
odoo/addons/website_legal_page/static/description/icon.png
odoo/addons/website_legal_page/static/description/index.html
odoo/addons/website_legal_page/static/description/johnny-automatic-scales-of-justice.svg
odoo/addons/website_legal_page/static/src/css/website_legal_page.scss
odoo/addons/website_legal_page/tests/__init__.py
odoo/addons/website_legal_page/tests/test_controller.py
odoo/addons/website_legal_page/views/assets.xml
odoo/addons/website_legal_page/views/reusable_templates.xml
odoo/addons/website_legal_page/views/website_legal_main_page.xml
odoo13_addon_website_legal_page-13.0.1.1.0.dist-info/METADATA
odoo13_addon_website_legal_page-13.0.1.1.0.dist-info/WHEEL
odoo13_addon_website_legal_page-13.0.1.1.0.dist-info/top_level.txt
odoo13_addon_website_legal_page-13.0.1.1.0.dist-info/RECORD
